marzpy/__init__.py
marzpy/marzban.py
marzpy/api/__init__.py
marzpy/api/admin.py
marzpy/api/core.py
marzpy/api/node.py
marzpy/api/send_requests.py
marzpy/api/subscription.py
marzpy/api/system.py
marzpy/api/template.py
marzpy/api/user.py
marzpy-0.0.5.dist-info/LICENSE
marzpy-0.0.5.dist-info/METADATA
marzpy-0.0.5.dist-info/WHEEL
marzpy-0.0.5.dist-info/top_level.txt
marzpy-0.0.5.dist-info/RECORD
